{
    "ADD_URL": "إضافة رابط",
    "ATTACH_MAXSIZE_VALIDATE": "يجب أن يكون حجم الملف أقل من:",
    "Blur": "طمس",
    "Blur Radius": "نصف القطر الضبابي",
    "Brush": "فرشاة",
    "CAMERA": "الة تصوير",
    "CANCEL": "إلغاء",
    "CHANGE_IMAGE": "تغيير الصورة",
    "CLEAR": "واضح",
    "COMPLETE": "اكتمال",
    "COMPLETE_EDITING": "التحرير الكامل",
    "Color Opacity": "عتامة اللون",
    "Crop": "ا & قتصاص",
    "DEFAULT": "افتراضي",
    "DELETE": "حذف",
    "EDIT": "تصحيح",
    "EDITOR_CODE": "الشفرة",
    "EDITOR_HEADER_1": "العنوان 1",
    "EDITOR_HEADER_2": "العنوان 2",
    "EDITOR_HEADER_3": "العنوان 3",
    "EDITOR_HEADER_4": "العنوان 4",
    "EDITOR_HEADER_5": "العنوان 5",
    "EDITOR_HEADER_6": "العنوان 6",
    "EDITOR_NORMAL": "طبيعي",
    "EDITOR_PT": "نقطة",
    "EDITOR_PX": "بكسل",
    "EDITOR_QUOTE": "يقتبس",
    "Emoji": "رمز تعبيري",
    "FILE": "ملف",
    "FILE_COMPRESSING_ER": "حدث خطأ أثناء ضغط الملف.",
    "FILE_DUPLICATE_ER": "الملف مرفق بالفعل. الرجاء اختيار ملف مختلف.",
    "FILE_PIXEL_SIZE_ER": "يجب أن يكون حجم بكسل الملف أقل من:",
    "FILE_PROCESSING_ER": "حدث خطأ أثناء معالجة ملف.",
    "FILE_SIZE_CALCULATING_ER": "حدث خطأ أثناء حساب حجم الملف.",
    "FILE_UNSUPPORTED": "نوع الملف هذا غير مسموح به",
    "Filter": "منقي",
    "Flip": "يواجه",
    "Freeform": "شكل حر",
    "GALLERY": "صالة عرض",
    "GIF": "GIF",
    "HIDE": "إخفاء",
    "IMAGE_PICKER_SEMANTIC_SELECTED": "منتقي الصور. تم تحديد الصورة",
    "IMAGE_PICKER_SEMANTIC_UNSELECTED": "منتقي الصور. لم يتم اختيار أي صورة",
    "Insert Your Message": "أدخل رسالتك",
    "LINK": "وصلة",
    "LINK_NAME": "اسم الرابط",
    "LINK_URL": "URL رابط",
    "MAX_ATTACH_MSG": "تم الوصول إلى الحد الأقصى للمرفق",
    "PICK_IMAGE": "اختر الصورة",
    "REMOVE": "إزالة",
    "RESET": "إعادة تعيين",
    "Reset": "إعادة تعيين",
    "Rotate left": "استدر يسارا",
    "Rotate right": "استدارة لليمين",
    "SAVE": "حفظ",
    "SHOW": "تبين",
    "SIZE ADJUST": "ضبط الحجم",
    "SLIDER FILTER COLOR": "لون الفلتر المنزلق",
    "SWIPE_TO_REVEAL_SEMANTIC": "اسحب لليسار للكشف عن الإجراءات",
    "Select Emoji": "حدد Emoji",
    "Slider Color": "لون المنزلق",
    "Slider White Black Color": "المنزلق أبيض اللون الأسود",
    "Square": "مربع",
    "TO": "إلى",
    "Text": "نص",
    "UNKNOWN": "مجهول",
    "URL_DUPLICATE_ER": "تم إرفاق URL بالفعل. الرجاء إدخال URL مختلف.",
    "URL_INVALID_ER": "الرجاء إدخال URL صالح.",
    "VIEW": "رأي"
}